morphit/__init__.py
morphit/utils.py
morphit/version.py
morphit-1.2.0.dist-info/LICENSE
morphit-1.2.0.dist-info/METADATA
morphit-1.2.0.dist-info/WHEEL
morphit-1.2.0.dist-info/top_level.txt
morphit-1.2.0.dist-info/RECORD
