Metadata-Version: 2.1
Name: morphit
Version: 1.2.0
Summary: makes shitty data more fit (a smarter serializer)
Home-page: https://github.com/PseudoSky/morphit
Author: pseudosky
Author-email: grepthesky@gmail.com
License: MIT
Keywords: serialize data schema transform parse parser parsing
Platform: UNKNOWN
Classifier: Topic :: Software Development :: Libraries
Classifier: Topic :: Utilities
Classifier: Topic :: Text Editors :: Text Processing
Classifier: Topic :: Text Processing
Requires-Dist: multipledispatch (>=0.4.9)
Requires-Dist: iso8601 (>=0.1.12)
